kucoin_websocket/__init__.py
kucoin_websocket/manager.py
kucoin_websocket/ws.py
kucoin_websocket/utils/__init__.py
kucoin_websocket/utils/base_request.py
kucoin_websocket/utils/threads.py
kucoin_websocket-1.0.3.dist-info/LICENSE
kucoin_websocket-1.0.3.dist-info/METADATA
kucoin_websocket-1.0.3.dist-info/WHEEL
kucoin_websocket-1.0.3.dist-info/top_level.txt
kucoin_websocket-1.0.3.dist-info/RECORD
