Metadata-Version: 2.1
Name: kucoin-websocket
Version: 1.0.3
Summary: Faster deployment is what we want!
Home-page: https://github.com/keivanipchihagh/kucoin-websocket
Author: Keivan Ipchi Hagh
Classifier: Programming Language :: Python :: 3
Classifier: License :: OSI Approved :: MIT License
Classifier: Operating System :: OS Independent
Requires-Python: >=3.8
License-File: LICENSE
Requires-Dist: APScheduler (==3.9.1)
Requires-Dist: certifi (==2022.9.24)
Requires-Dist: charset-normalizer (==2.1.1)
Requires-Dist: idna (==3.4)
Requires-Dist: pytz (==2022.4)
Requires-Dist: pytz-deprecation-shim (==0.1.0.post0)
Requires-Dist: requests (==2.28.1)
Requires-Dist: six (==1.16.0)
Requires-Dist: tzdata (==2022.4)
Requires-Dist: tzlocal (==4.2)
Requires-Dist: urllib3 (==1.26.12)
Requires-Dist: websockets (==10.3)
